{"users_completed": 35, "rating": "G", "studios": [], "members": 135, "score_6_votes": 2, "users_plan_to_watch": 64, "score_9_votes": 1, "users_total": 135, "rank": 10871, "episodes": 51, "duration": 5.0, "related_ids": [14631, 22709, 23313], "id": 10987, "category": "anime", "genres": ["Comedy", "Kids"], "score_1_votes": 0, "title": "Zettai Zetsumei Dangerous Jiisan (2004)", "score_10_votes": 0, "source": "Unknown", "users_dropped": 22, "score": 6.55, "score_total_votes": 22, "type": "TV", "status": "Finished Airing", "users_onhold": 10, "score_5_votes": 3, "broadcast": "Unknown", "score_7_votes": 8, "favorites": 0, "score_4_votes": 2, "producers": [], "licensors": [], "score_3_votes": 1, "url": "https://myanimelist.net/anime/10987/Zettai_Zetsumei_Dangerous_Jiisan_2004", "popularity": 10031, "score_users": 20, "premiered": "Spring 2004", "aired_end": "2005-03-27T00:00:00", "aired_start": "2004-04-04T00:00:00", "synopsis": "Grandpa Danger is a world where the great protector is Grandpa Danger! He's an expert at falling off of cliffs, dealing with a principal who suffers from a severe inferiority complex, and escaping the hidden dangers of sleep! He's a nonsensical, utterly disgusting, relentless prankster. Grandpa Danger's excessive phlegm and farts frustrate Grandson to hilarious extremes, and make you laugh until your stomach splits! (Source: AniDB)", "score_8_votes": 5, "users_watching": 4, "score_2_votes": 0}