{"rating": "PG-13", "studios": ["Seven"], "members": 16614, "rank": 6865, "episodes": 13, "duration": 3.0, "id": 16169, "category": "anime", "genres": ["Comedy", "Slice of Life"], "title": "Choboraunyopomi Gekijou Ai Mai Mii", "source": "4-koma manga", "score": 5.83, "type": "TV", "status": "Finished Airing", "broadcast": "Unknown", "favorites": 28, "producers": ["Dream Creation"], "licensors": [], "url": "https://myanimelist.net/anime/16169/Choboraunyopomi_Gekijou_Ai_Mai_Mii", "popularity": 2300, "score_users": 7472, "premiered": "Winter 2013", "aired_end": "2013-03-27T00:00:00", "aired_start": "2013-01-03T00:00:00", "synopsis": "The anime adaptation of the four-panel manga \"Ai Mai Mii\". The story follows girls in a manga club\u2014Ai, Mai, Mii, and Ponoka-senpai\u2014who might be fighting evil invaders threatening Earth, facing off against rivals in tournaments, and dealing with other absurd situations when they are not drawing manga. (Source: ANN)"}