{"Score 10 votes": 135, "rating": "Rx", "studios": [], "members": 2988, "Users On-Hold": 121, "Users Completed": 1821, "Total Votes": 1320, "Users Watching": 221, "rank": null, "episodes": 1, "duration": 22.0, "id": 16189, "category": "anime", "Score 9 votes": 126, "genres": ["Hentai"], "Score 2 votes": 14, "title": "Miboujin Nikki: Akogare no Ano Hito to Hitotsu Yane no Shita", "source": "Visual novel", "score": 6.94, "Users Total": 2988, "Score 1 votes": 14, "type": "OVA", "Users Dropped": 84, "status": "Finished Airing", "related_titles": [], "Score 8 votes": 246, "Score 5 votes": 145, "broadcast": null, "Users Plan to Watch": 741, "Score 3 votes": 30, "favorites": 25, "Score 4 votes": 50, "producers": ["Pink Pineapple"], "licensors": [], "Score 7 votes": 336, "url": "https://myanimelist.net/anime/16189/Miboujin_Nikki__Akogare_no_Ano_Hito_to_Hitotsu_Yane_no_Shita", "popularity": 4832, "score_users": 1271, "premiered": null, "aired_end": "2013-01-25T00:00:00", "aired_start": "2013-01-25T00:00:00", "synopsis": "Based on the erotic game by Orcsoft. Ever since Ayako's husband died, Akito took it upon himself to guard her as his cousin. However, he suddenly realized that this situation can lead to something even more intimate... Will his virginity be in trouble? (Source: HentaiTake)", "Score 6 votes": 224}