{"rating": "G", "studios": [], "members": 586, "rank": 6643, "episodes": 39, "duration": 3.0, "id": 17733, "category": "anime", "genres": ["Comedy", "Slice of Life"], "title": "Dibetagurashi: Ahiru no Seikatsu", "source": "Unknown", "score": 5.98, "type": "TV", "status": "Finished Airing", "broadcast": "Unknown", "favorites": 0, "producers": [], "licensors": [], "url": "https://myanimelist.net/anime/17733/Dibetagurashi__Ahiru_no_Seikatsu", "popularity": 7708, "score_users": 52, "premiered": "Spring 2013", "aired_end": "2014-03-30T00:00:00", "aired_start": "2013-04-07T00:00:00", "synopsis": "The story follows the daily life of a group of birds, including a duck, an old nihilistic great grey owl, and a gluttonous Caique parrot. (Source: ANN)"}