{"users_completed": 4425, "rating": "PG-13", "studios": ["Hotline"], "members": 6647, "score_6_votes": 873, "users_plan_to_watch": 1062, "score_9_votes": 88, "users_total": 6647, "rank": 7263, "episodes": 12, "duration": 3.0, "related_ids": [], "id": 17849, "category": "anime", "genres": ["Comedy"], "score_1_votes": 119, "title": "Sparrow's Hotel", "score_10_votes": 71, "source": "4-koma manga", "users_dropped": 673, "score": 5.59, "score_total_votes": 3768, "type": "TV", "status": "Finished Airing", "users_onhold": 159, "score_5_votes": 793, "broadcast": "Unknown", "score_7_votes": 659, "favorites": 5, "score_4_votes": 419, "producers": ["DAX Production", "Dream Creation"], "licensors": [], "score_3_votes": 259, "url": "https://myanimelist.net/anime/17849/Sparrows_Hotel", "popularity": 3548, "score_users": 3496, "premiered": "Spring 2013", "aired_end": "2013-06-25T00:00:00", "aired_start": "2013-04-09T00:00:00", "synopsis": "The comedy revolves around Sayuri Satou, the new front desk worker at the Sparrow's Hotel\u2014\"the closest hotel to Heaven\". Her special features are her large breasts and her skills of assassination. She takes down people who cause trouble in the business hotel with those skills, but she is in fact very unskilled when talking to the male hotel manager, and often bites her tongue. (Source: ANN)", "score_8_votes": 285, "users_watching": 328, "score_2_votes": 202}