{"rating": "None", "studios": ["DLE"], "members": 109, "rank": 10401, "episodes": 1, "duration": 110.0, "id": 19535, "category": "anime", "genres": ["Comedy", "Parody", "Super Power"], "title": "Takanotsume GO: Utsukushiki Elleair Shoushuu Plus", "source": "Unknown", "score": 7.4, "type": "Movie", "status": "Finished Airing", "broadcast": null, "favorites": 1, "producers": [], "licensors": [], "url": "https://myanimelist.net/anime/19535/Takanotsume_GO__Utsukushiki_Elleair_Shoushuu_Plus", "popularity": 10325, "score_users": 5, "premiered": null, "aired_end": "2013-09-13T00:00:00", "aired_start": "2013-09-13T00:00:00", "synopsis": "Yoshida-kun and members of the Eagle Talon secret society step up to defend the humankind from evil invaders."}