{"rating": "Rx", "studios": [], "members": 2060, "rank": null, "episodes": 1, "duration": 25.0, "id": 19857, "category": "anime", "genres": ["Hentai"], "title": "Kagachi-sama Onagusame Tatematsurimasu: Netorare Mura Inya Hanashi The Animation", "source": "Visual novel", "score": 6.37, "type": "OVA", "status": "Finished Airing", "broadcast": null, "favorites": 11, "producers": ["Pink Pineapple"], "licensors": [], "url": "https://myanimelist.net/anime/19857/Kagachi-sama_Onagusame_Tatematsurimasu__Netorare_Mura_Inya_Hanashi_The_Animation", "popularity": 5509, "score_users": 771, "premiered": null, "aired_end": "2013-10-25T00:00:00", "aired_start": "2013-10-25T00:00:00", "synopsis": "On the 2nd anniversary of the marriage, Takahiko realizes that he is no longer getting sexually excited with his beloved wife, Manami. He is aware that this impotence is because of the strange custom he witnessed in his hometown, where a naughty feast takes place every night in the dark throughout the summer festival. Long ago, he ran out of his hometown, horrified, but now he realizes that he can cure himself only by going back to that place... Beloved young wife and the beautiful step mother he adores, pant in the pleasure given by someone else! The lewd netori festival of night begins... (Source: DLsite) Based on the adult PC game by Orcsoft."}