{"users_completed": 18, "rating": "PG-13", "studios": [], "members": 78, "score_6_votes": 1, "users_plan_to_watch": 41, "score_9_votes": 0, "users_total": 78, "rank": 10187, "episodes": 13, "duration": 10.0, "related_ids": [33193, 33195, 33196], "id": 33194, "category": "anime", "genres": ["Comedy", "Parody"], "score_1_votes": 0, "title": "Shi Wan Ge Leng Xiaohua 2nd Season", "score_10_votes": 2, "source": "Web manga", "users_dropped": 10, "score": 6.33, "score_total_votes": 10, "type": "ONA", "status": "Finished Airing", "users_onhold": 3, "score_5_votes": 0, "broadcast": null, "score_7_votes": 4, "favorites": 0, "score_4_votes": 0, "producers": ["Yaoqi"], "licensors": [], "score_3_votes": 1, "url": "https://myanimelist.net/anime/33194/Shi_Wan_Ge_Leng_Xiaohua_2nd_Season", "popularity": 11130, "score_users": 9, "premiered": null, "aired_end": "2014-12-30T00:00:00", "aired_start": "2013-12-31T00:00:00", "synopsis": "Second season of One Hundred Thousand Bad Jokes .", "score_8_votes": 1, "users_watching": 6, "score_2_votes": 1}