{"rating": "G", "studios": [], "members": 68, "rank": 10119, "episodes": 1, "duration": 2.0, "id": 29393, "category": "anime", "genres": ["Adventure"], "title": "Pinky Monkey no Umareta Hi", "source": "Unknown", "score": 4.17, "type": "ONA", "status": "Finished Airing", "broadcast": null, "favorites": 0, "producers": [], "licensors": [], "url": "https://myanimelist.net/anime/29393/Pinky_Monkey_no_Umareta_Hi", "popularity": 11311, "score_users": 23, "premiered": null, "aired_end": "2006-04-30T00:00:00", "aired_start": "2006-04-30T00:00:00", "synopsis": "Produced by Kenji Eno, commissioned by Frente International, this short shows the birth of Pinky."}