{"users_completed": 43040, "rating": "PG-13", "studios": ["Group TAC"], "members": 65050, "score_6_votes": 3851, "users_plan_to_watch": 18571, "score_9_votes": 6379, "users_total": 65050, "rank": 1079, "episodes": 6, "duration": 24.0, "related_ids": [], "id": 587, "category": "anime", "genres": ["Comedy", "Drama", "Romance"], "score_1_votes": 79, "title": "Hanbun no Tsuki ga Noboru Sora", "score_10_votes": 4235, "source": "Light novel", "users_dropped": 869, "score": 7.69, "score_total_votes": 35157, "type": "TV", "status": "Finished Airing", "users_onhold": 1212, "score_5_votes": 1761, "broadcast": "Unknown", "score_7_votes": 8141, "favorites": 412, "score_4_votes": 610, "producers": ["Pony Canyon", "Dream Force"], "licensors": ["Nozomi Entertainment", "Crimson Star Media"], "score_3_votes": 255, "url": "https://myanimelist.net/anime/587/Hanbun_no_Tsuki_ga_Noboru_Sora", "popularity": 905, "score_users": 34622, "premiered": "Winter 2006", "aired_end": "2006-02-24T00:00:00", "aired_start": "2006-01-13T00:00:00", "synopsis": "After contracting hepatitis A, Ezaki Yuuichi has been confined to a hospital, away from his friends and family, much to his displeasure. To relieve his boredom, he has taken to sneaking out of the hospital, usually putting himself on the receiving end of a beating from his nurse. Upon meeting a girl his age also staying in the hospital, he is immediately captivated by her beauty. Akiba Rika's personality is not quite as captivating as her beauty however. In fact, she is rather selfish, moody, and bossy. But as the two spend more time with each other, they become closer, sharing the ordinary joys and trials of a budding teenage romance, even when darkened with impending tragedy\u2014for Rika's condition does not leave her much longer to live. [Written by MAL Rewrite]", "score_8_votes": 9708, "users_watching": 1358, "score_2_votes": 138}