{"rating": "PG-13", "studios": [], "members": 972, "rank": 5707, "episodes": 1, "duration": 17.0, "id": 8533, "category": "anime", "genres": ["Demons", "Drama", "Historical", "Romance"], "title": "Hana no Kage", "source": "Unknown", "score": 6.38, "type": "ONA", "status": "Finished Airing", "broadcast": null, "favorites": 1, "producers": [], "licensors": [], "url": "https://myanimelist.net/anime/8533/Hana_no_Kage", "popularity": 6912, "score_users": 267, "premiered": null, "aired_end": "2006-04-01T00:00:00", "aired_start": "2006-04-01T00:00:00", "synopsis": "In ancient Japan, a princess and her lover run away from their pursuers. When it became apparent that they would be caught, they vowed to commit suicide rather than have the princess return to her former life. Both of them took their blades to end their lives but something went wrong. Now one of them seeks revenge for being abandoned."}