{"users_completed": 1271, "rating": "R", "studios": [], "members": 2008, "score_6_votes": 237, "users_plan_to_watch": 615, "score_9_votes": 46, "users_total": 2008, "rank": 6183, "episodes": 2, "duration": 27.0, "related_ids": [495], "id": 1228, "category": "anime", "genres": ["Action", "Comedy", "Ecchi", "Fantasy", "Supernatural"], "score_1_votes": 12, "title": "Chivas 1-2-3", "score_10_votes": 33, "source": "Manga", "users_dropped": 35, "score": 6.22, "score_total_votes": 961, "type": "OVA", "status": "Finished Airing", "users_onhold": 42, "score_5_votes": 168, "broadcast": null, "score_7_votes": 254, "favorites": 0, "score_4_votes": 77, "producers": ["Daume", "Teichiku Entertainment"], "licensors": ["ADV Films"], "score_3_votes": 19, "url": "https://myanimelist.net/anime/1228/Chivas_1-2-3", "popularity": 5620, "score_users": 950, "premiered": null, "aired_end": "1999-09-21T00:00:00", "aired_start": "1999-08-21T00:00:00", "synopsis": "Ruthless sorcerer Chivas Scotch is hired by a count named Cuttlefish to destroy an evil monster attacking a nearby village. But things go awry when Chivas fails to destroy the monster and he's forced to transfer his spirit in the body of his beautiful servant Gin Fizz. (Source: ANN)", "score_8_votes": 97, "users_watching": 45, "score_2_votes": 18}