{"rating": "PG-13", "studios": [], "members": 3251, "rank": 3256, "episodes": 1, "duration": 92.0, "id": 1431, "category": "anime", "genres": ["Action", "Adventure", "Comedy", "Shounen"], "title": "Lupin III: Ai no Da Capo - Fujiko's Unlucky Days", "source": "Unknown", "score": 7.04, "type": "Special", "status": "Finished Airing", "broadcast": null, "favorites": 1, "producers": ["VAP", "Tokyo Movie Shinsha", "Tohokushinsha Film Corporation"], "licensors": ["FUNimation Entertainment"], "url": "https://myanimelist.net/anime/1431/Lupin_III__Ai_no_Da_Capo_-_Fujikos_Unlucky_Days", "popularity": 4654, "score_users": 1342, "premiered": null, "aired_end": "1999-07-30T00:00:00", "aired_start": "1999-07-30T00:00:00", "synopsis": "When Fujiko acquires and memorizes papers called the Columbus Files, she is attacked and loses her memory. Lupin, a treasure hunter named Rosaria, and the cackling villain Nazaroff all pursue Fujiko, as she is the only key to the location of Columbus' Egg, a treasure connected to the mysterious Orgone Energy. (Source: ANN)"}