{"users_completed": 1393, "rating": "Rx", "studios": [], "members": 2545, "score_6_votes": 220, "users_plan_to_watch": 787, "score_9_votes": 71, "users_total": 2545, "rank": null, "episodes": 2, "duration": 30.0, "related_ids": [], "id": 7581, "category": "anime", "genres": ["Hentai"], "score_1_votes": 19, "title": "Otome Chibaku Yuugi", "score_10_votes": 74, "source": "Visual novel", "users_dropped": 80, "score": 6.56, "score_total_votes": 932, "type": "OVA", "status": "Finished Airing", "users_onhold": 115, "score_5_votes": 113, "broadcast": null, "score_7_votes": 221, "favorites": 7, "score_4_votes": 45, "producers": ["Suzuki Mirano"], "licensors": [], "score_3_votes": 25, "url": "https://myanimelist.net/anime/7581/Otome_Chibaku_Yuugi", "popularity": 5152, "score_users": 890, "premiered": null, "aired_end": "2010-03-26T00:00:00", "aired_start": "2010-01-29T00:00:00", "synopsis": "Kaoru is a high school student who does not have the guts to go against his old friend Nanao. Nanao keeps giving Kaoru sexual orders which he is forced to obey. One day he decides to take revenge. And for the revenge he will use his other classmate Mayu as his trump card.", "score_8_votes": 127, "users_watching": 170, "score_2_votes": 17}