{"users_completed": 1153, "rating": "Rx", "studios": [], "members": 2433, "score_6_votes": 187, "users_plan_to_watch": 829, "score_9_votes": 57, "users_total": 2433, "rank": null, "episodes": 1, "duration": 30.0, "related_ids": [], "id": 9588, "category": "anime", "genres": ["Hentai"], "score_1_votes": 17, "title": "Kyouiku Shidou The Animation", "score_10_votes": 61, "source": "Visual novel", "users_dropped": 89, "score": 6.5, "score_total_votes": 791, "type": "OVA", "status": "Finished Airing", "users_onhold": 115, "score_5_votes": 92, "broadcast": null, "score_7_votes": 170, "favorites": 9, "score_4_votes": 48, "producers": ["Milky Animation Label", "MS Pictures"], "licensors": [], "score_3_votes": 20, "url": "https://myanimelist.net/anime/9588/Kyouiku_Shidou_The_Animation", "popularity": 5232, "score_users": 753, "premiered": null, "aired_end": "2010-11-19T00:00:00", "aired_start": "2010-11-19T00:00:00", "synopsis": "Yoshiyuki loves having sex with girls. He is now a teacher and enjoys sex life with female students. Now that he has had sex with almost all of students, he decides to move to a different school. His next school is a famous girls' school.... He meets various pretty girls there and soon plans to give \"educational guidance\" to them.... (Source: ErogeShop)", "score_8_votes": 123, "users_watching": 247, "score_2_votes": 16}