{"rating": "G", "studios": ["Madhouse"], "members": 3178, "rank": 3780, "episodes": 48, "duration": 8.0, "id": 1597, "category": "anime", "genres": ["Comedy"], "title": "Panyo Panyo Di Gi Charat", "source": "Unknown", "score": 6.89, "type": "TV", "status": "Finished Airing", "broadcast": "Unknown", "favorites": 12, "producers": ["Broccoli"], "licensors": [], "url": "https://myanimelist.net/anime/1597/Panyo_Panyo_Di_Gi_Charat", "popularity": 4695, "score_users": 985, "premiered": "Winter 2002", "aired_end": "2003-04-03T00:00:00", "aired_start": "2002-01-05T00:00:00", "synopsis": "Deijiko is the princess of the planet of Di Gi Charat. After reading a book, she is influenced to want to help everyone be happy. She leaves the castle and pretends to be a normal girl. She tries to make everyone happy by taking various jobs around the town and thereby making all sorts of new friends and inevitably, enemies. (Source: ANN)"}