{"users_completed": 4098, "rating": "PG-13", "studios": ["Toei Animation"], "members": 6125, "score_6_votes": 622, "users_plan_to_watch": 840, "score_9_votes": 299, "users_total": 6125, "rank": 3556, "episodes": 51, "duration": 24.0, "related_ids": [3281, 5967, 6310, 12279, 6310], "id": 1707, "category": "anime", "genres": ["Action", "Sci-Fi", "Comedy", "Sports", "Martial Arts", "Shounen"], "score_1_votes": 37, "title": "Kinnikuman II Sei", "score_10_votes": 225, "source": "Manga", "users_dropped": 658, "score": 6.95, "score_total_votes": 3577, "type": "TV", "status": "Finished Airing", "users_onhold": 345, "score_5_votes": 348, "broadcast": "Unknown", "score_7_votes": 1074, "favorites": 31, "score_4_votes": 158, "producers": ["TV Tokyo", "Yomiuri Advertising"], "licensors": ["4Kids Entertainment"], "score_3_votes": 71, "url": "https://myanimelist.net/anime/1707/Kinnikuman_II_Sei", "popularity": 3670, "score_users": 3292, "premiered": "Winter 2002", "aired_end": "2002-12-25T00:00:00", "aired_start": "2002-01-09T00:00:00", "synopsis": "Kinnikuman II Sei takes place several years after the events of the original Kinnikuman . Mantarou Kinniku is the 59th prince of Planet Kinniku and son of the renowned wrestler, King Suguru. Lazy, immature, and cowardly, Mantarou seems to have little in common with his heroic father. When a powerful group calling themselves the dMP threatens the Earth, only someone as powerful as Kinnikuman stands a chance against them. Not knowing the current whereabouts of the King, a plan is formed to have his son Mantarou take up the mantle. The idea of fighting super villains does not sit well with Mantarou, who initially runs away from his duty. He flees to Earth where he encounters Meat, his father\u2019s old trainer. Despite Mantarou's shortcomings, Meat sees King Suguru in him, and believes he can set the prince on the right path. Thus begins Mantarou's journey to better himself and save the world.", "score_8_votes": 717, "users_watching": 184, "score_2_votes": 26}