{"rating": "PG-13", "studios": ["Madhouse"], "members": 8467, "rank": 4560, "episodes": 4, "duration": 13.0, "id": 1980, "category": "anime", "genres": ["Action", "Comedy", "Mecha", "Sci-Fi", "Space"], "title": "Trava: Fist Planet", "source": "Unknown", "score": 6.7, "type": "OVA", "status": "Finished Airing", "broadcast": null, "favorites": 24, "producers": [], "licensors": [], "url": "https://myanimelist.net/anime/1980/Trava__Fist_Planet", "popularity": 3178, "score_users": 3944, "premiered": null, "aired_end": "2002-07-03T00:00:00", "aired_start": "2002-03-02T00:00:00", "synopsis": "Ace pilot Trava and his personal mechanic buddy Shinkai, on their way to mark an out-of-the-way planet, pick up Mikuru, a girl with no memory. The three are about to discover that the planet is more than it seems. (Source: ANN)"}