{"rating": "G", "studios": [], "members": 135, "rank": 8363, "episodes": 1, "duration": 61.0, "id": 8403, "category": "anime", "genres": ["Drama"], "title": "Bonobono: Kumomo no Ki no Koto", "source": "4-koma manga", "score": 5.96, "type": "Movie", "status": "Finished Airing", "broadcast": null, "favorites": 0, "producers": ["Amuse Pictures"], "licensors": [], "url": "https://myanimelist.net/anime/8403/Bonobono__Kumomo_no_Ki_no_Koto", "popularity": 9918, "score_users": 24, "premiered": null, "aired_end": "2002-08-10T00:00:00", "aired_start": "2002-08-10T00:00:00", "synopsis": "The second theatrical Bonobono movie, done completely in 3D."}