{"users_completed": 5009, "rating": "G", "studios": ["SANZIGEN", "LIDENFILMS"], "members": 7884, "score_6_votes": 890, "users_plan_to_watch": 1883, "score_9_votes": 241, "users_total": 7884, "rank": 4685, "episodes": 13, "duration": 7.0, "related_ids": [30384], "id": 31560, "category": "anime", "genres": ["Comedy", "Music", "Slice of Life"], "score_1_votes": 21, "title": "Miss Monochrome: The Animation 3", "score_10_votes": 143, "source": "Original", "users_dropped": 200, "score": 6.66, "score_total_votes": 3852, "type": "TV", "status": "Finished Airing", "users_onhold": 242, "score_5_votes": 504, "broadcast": "Fridays at 22:30 (JST)", "score_7_votes": 1182, "favorites": 5, "score_4_votes": 138, "producers": ["Starchild Records", "Magic Capsule"], "licensors": [], "score_3_votes": 66, "url": "https://myanimelist.net/anime/31560/Miss_Monochrome__The_Animation_3", "popularity": 3308, "score_users": 3733, "premiered": "Fall 2015", "aired_end": "2015-12-25T00:00:00", "aired_start": "2015-10-02T00:00:00", "synopsis": "Third season of Miss Monochrome: The Animation .", "score_8_votes": 631, "users_watching": 550, "score_2_votes": 36}