{"users_completed": 5829, "rating": "G", "studios": ["A-1 Pictures"], "members": 8948, "score_6_votes": 832, "users_plan_to_watch": 2757, "score_9_votes": 321, "users_total": 8948, "rank": 3965, "episodes": 2, "duration": 2.0, "related_ids": [10521, 33094], "id": 10532, "category": "anime", "genres": ["Comedy"], "score_1_votes": 29, "title": "Working'!! Announcement Specials", "score_10_votes": 247, "source": "4-koma manga", "users_dropped": 74, "score": 6.84, "score_total_votes": 3824, "type": "ONA", "status": "Finished Airing", "users_onhold": 128, "score_5_votes": 442, "broadcast": null, "score_7_votes": 1169, "favorites": 7, "score_4_votes": 100, "producers": [], "licensors": [], "score_3_votes": 40, "url": "https://myanimelist.net/anime/10532/Working_Announcement_Specials", "popularity": 3132, "score_users": 3759, "premiered": null, "aired_end": "2011-04-02T00:00:00", "aired_start": "2011-04-01T00:00:00", "synopsis": "Several characters announce the new season. Episode 1 - April Fool Announcement (Hana and Daisuke) Episode 2 - True Announcement (Aoi, Popura, and Souta)", "score_8_votes": 616, "users_watching": 160, "score_2_votes": 28}