{"rating": "Rx", "studios": [], "members": 1555, "rank": null, "episodes": 2, "duration": 30.0, "id": 10728, "category": "anime", "genres": ["Hentai"], "title": "Maid Ane", "source": "Manga", "score": 6.26, "type": "OVA", "status": "Finished Airing", "broadcast": null, "favorites": 2, "producers": ["Digital Works"], "licensors": [], "url": "https://myanimelist.net/anime/10728/Maid_Ane", "popularity": 6075, "score_users": 628, "premiered": null, "aired_end": "2011-12-16T00:00:00", "aired_start": "2011-08-19T00:00:00", "synopsis": "One day Yuuta comes home to find his childhood friend Akie has returned to his country village. Akie works as a maid in Tokyo and Yuuta begins thinking of her in a whole different light. (Source: ANN)"}