{"users_completed": 3140, "rating": "PG-13", "studios": ["David Production"], "members": 6710, "score_6_votes": 546, "users_plan_to_watch": 2467, "score_9_votes": 139, "users_total": 6710, "rank": 6278, "episodes": 6, "duration": 9.0, "related_ids": [10396], "id": 12447, "category": "anime", "genres": ["Comedy"], "score_1_votes": 59, "title": "Ben-To Picture Drama", "score_10_votes": 149, "source": "Light novel", "users_dropped": 301, "score": 6.18, "score_total_votes": 2406, "type": "Special", "status": "Finished Airing", "users_onhold": 479, "score_5_votes": 426, "broadcast": null, "score_7_votes": 448, "favorites": 4, "score_4_votes": 182, "producers": ["AT-X"], "licensors": [], "score_3_votes": 84, "url": "https://myanimelist.net/anime/12447/Ben-To_Picture_Drama", "popularity": 3531, "score_users": 2320, "premiered": null, "aired_end": "2012-05-16T00:00:00", "aired_start": "2011-12-21T00:00:00", "synopsis": "Picture dramas from the DVD/BDs.", "score_8_votes": 312, "users_watching": 323, "score_2_votes": 61}