{"users_completed": 2355, "rating": "PG-13", "studios": ["Madhouse"], "members": 3613, "score_6_votes": 329, "users_plan_to_watch": 1129, "score_9_votes": 140, "users_total": 3613, "rank": 4133, "episodes": 1, "duration": 5.0, "related_ids": [6675], "id": 11483, "category": "anime", "genres": ["Cars", "Sports"], "score_1_votes": 19, "title": "Redline Pilot", "score_10_votes": 92, "source": "Original", "users_dropped": 39, "score": 6.8, "score_total_votes": 1639, "type": "Special", "status": "Finished Airing", "users_onhold": 40, "score_5_votes": 179, "broadcast": null, "score_7_votes": 511, "favorites": 2, "score_4_votes": 57, "producers": [], "licensors": [], "score_3_votes": 25, "url": "https://myanimelist.net/anime/11483/Redline_Pilot", "popularity": 4504, "score_users": 1626, "premiered": null, "aired_end": "2009-01-12T00:00:00", "aired_start": "2009-01-12T00:00:00", "synopsis": "Pilot episode for the movie.", "score_8_votes": 276, "users_watching": 50, "score_2_votes": 11}