{"rating": "G", "studios": [], "members": 100, "rank": 10170, "episodes": 1, "duration": 15.0, "id": 14069, "category": "anime", "genres": ["Kids"], "title": "Shinjuku Shin-chan: Yoiko no Koutsuu Anzen", "source": "Unknown", "score": 4.82, "type": "ONA", "status": "Finished Airing", "broadcast": null, "favorites": 0, "producers": [], "licensors": [], "url": "https://myanimelist.net/anime/14069/Shinjuku_Shin-chan__Yoiko_no_Koutsuu_Anzen", "popularity": 10515, "score_users": 28, "premiered": null, "aired_end": "2009-08-25T00:00:00", "aired_start": "2009-08-25T00:00:00", "synopsis": "Shinjuku Shin-chan teaches kids about traffic safety."}