{"users_completed": 13740, "rating": "PG-13", "studios": ["A-1 Pictures"], "members": 18767, "score_6_votes": 1628, "users_plan_to_watch": 4657, "score_9_votes": 1102, "users_total": 18767, "rank": 2516, "episodes": 1, "duration": 28.0, "related_ids": [317, 2952], "id": 6151, "category": "anime", "genres": ["Action", "Fantasy", "Super Power"], "score_1_votes": 32, "title": "Final Fantasy VII: On the Way to a Smile - Episode: Denzel", "score_10_votes": 707, "source": "Novel", "users_dropped": 65, "score": 7.24, "score_total_votes": 9952, "type": "OVA", "status": "Finished Airing", "users_onhold": 153, "score_5_votes": 685, "broadcast": null, "score_7_votes": 3147, "favorites": 11, "score_4_votes": 174, "producers": ["Square Enix"], "licensors": [], "score_3_votes": 71, "url": "https://myanimelist.net/anime/6151/Final_Fantasy_VII__On_the_Way_to_a_Smile_-_Episode__Denzel", "popularity": 2184, "score_users": 9868, "premiered": null, "aired_end": "2009-04-16T00:00:00", "aired_start": "2009-04-16T00:00:00", "synopsis": "Final Fantasy VII spinoff novel On the Way to a Smile Episode: Denzel will be adapted into an anime for the Final Fantasy VII: Advent Children Complete release on April 16. The anime will ship as an extra supplement on Advent Children's Blu-ray Disc releases. The Denzel part of On the Way to a Smile story begins as the character Denzel aims to enlist in the World Regenesis Organization (WRO) and \"leaps\" back into Denzel's past. (Source: ANN)", "score_8_votes": 2365, "users_watching": 152, "score_2_votes": 41}