{"users_completed": 35266, "rating": "PG-13", "studios": ["Artland"], "members": 48917, "score_6_votes": 537, "users_plan_to_watch": 12443, "score_9_votes": 9749, "users_total": 48917, "rank": 49, "episodes": 1, "duration": 45.0, "related_ids": [457, 21939], "id": 21329, "category": "anime", "genres": ["Slice of Life", "Adventure", "Fantasy", "Supernatural", "Historical", "Mystery", "Seinen"], "score_1_votes": 50, "title": "Mushishi Special: Hihamukage", "score_10_votes": 6524, "source": "Unknown", "users_dropped": 132, "score": 8.66, "score_total_votes": 27438, "type": "Special", "status": "Finished Airing", "users_onhold": 374, "score_5_votes": 132, "broadcast": null, "score_7_votes": 2643, "favorites": 83, "score_4_votes": 26, "producers": ["Aniplex", "Kodansha", "Delfi Sound"], "licensors": [], "score_3_votes": 17, "url": "https://myanimelist.net/anime/21329/Mushishi_Special__Hihamukage", "popularity": 1148, "score_users": 27274, "premiered": null, "aired_end": "2014-01-04T00:00:00", "aired_start": "2014-01-04T00:00:00", "synopsis": "A 45-minute special which adapts a two-chapter manga. Ginko finds himself in a village which falls victim to a mushi that blocks out the sun; however, one villager seems to benefit from this calamity.", "score_8_votes": 7748, "users_watching": 702, "score_2_votes": 12}