{"rating": "PG-13", "studios": ["ufotable"], "members": 22985, "rank": 1513, "episodes": 1, "duration": 44.0, "id": 24459, "category": "anime", "genres": ["Fantasy"], "title": "Tales of Zestiria: Doushi no Yoake", "source": "Game", "score": 7.52, "type": "Special", "status": "Finished Airing", "broadcast": null, "favorites": 46, "producers": [], "licensors": [], "url": "https://myanimelist.net/anime/24459/Tales_of_Zestiria__Doushi_no_Yoake", "popularity": 1895, "score_users": 11909, "premiered": null, "aired_end": "2014-12-30T00:00:00", "aired_start": "2014-12-30T00:00:00", "synopsis": "TV anime special of Bandai Namco Games' Tales of Zestiria role-playing game."}