{"rating": "PG", "studios": ["Xebec", "OLM"], "members": 273, "rank": 5733, "episodes": 1, "duration": 24.0, "id": 24675, "category": "anime", "genres": ["Game"], "title": "Future Card Buddyfight Recap", "source": "Unknown", "score": 6.35, "type": "Special", "status": "Finished Airing", "broadcast": null, "favorites": 0, "producers": ["Bushiroad"], "licensors": [], "url": "https://myanimelist.net/anime/24675/Future_Card_Buddyfight_Recap", "popularity": 8864, "score_users": 82, "premiered": null, "aired_end": "2014-06-14T00:00:00", "aired_start": "2014-06-14T00:00:00", "synopsis": "Recap episode aired between episodes 23 and 24."}