{"rating": "PG-13", "studios": ["A-1 Pictures"], "members": 42513, "rank": 591, "episodes": 24, "duration": 24.0, "id": 25517, "category": "anime", "genres": ["Adventure", "Comedy", "Romance", "Shounen"], "title": "Magic Kaito 1412", "source": "Manga", "score": 7.95, "type": "TV", "status": "Finished Airing", "broadcast": "Saturdays at 17:30 (JST)", "favorites": 417, "producers": ["Aniplex", "Yomiuri Telecasting Corporation", "DAX Production"], "licensors": [], "url": "https://myanimelist.net/anime/25517/Magic_Kaito_1412", "popularity": 1274, "score_users": 17635, "premiered": "Fall 2014", "aired_end": "2015-03-28T00:00:00", "aired_start": "2014-10-04T00:00:00", "synopsis": "Eight years after the mysterious death of his father, Kaito Kuroba, a slightly mischievous but otherwise ordinary teenager, discovers a shocking secret: the Phantom Thief Kaito Kid\u2014also known as \"The Magician Under the Moonlight\"\u2014was none other than his own father. The former thief was murdered by a criminal organization seeking a mythical stone called the Pandora Gem, said to shed a tear with the passing of the Valley Comet that comes every ten thousand years. When the tear is consumed, the gem supposedly grants immortality. Vowing to bring those responsible for his father's death to justice, Kaito dons the Phantom Thief's disguise, stealing priceless jewels night after night to find the Pandora Gem before his enemies can use the power for themselves. [Written by MAL Rewrite]"}