{"users_completed": 78, "rating": "PG-13", "studios": ["J.C.Staff"], "members": 362, "score_6_votes": 15, "users_plan_to_watch": 243, "score_9_votes": 1, "users_total": 362, "rank": 6438, "episodes": 2, "duration": 25.0, "related_ids": [3805, 10217, 33532], "id": 27997, "category": "anime", "genres": ["Magic"], "score_1_votes": 2, "title": "Kaitou Tenshi Twin Angel: Kyun Kyun\u2606Tokimeki Paradise!! OVA", "score_10_votes": 3, "source": "Unknown", "users_dropped": 10, "score": 6.11, "score_total_votes": 56, "type": "OVA", "status": "Finished Airing", "users_onhold": 12, "score_5_votes": 9, "broadcast": null, "score_7_votes": 6, "favorites": 1, "score_4_votes": 9, "producers": [], "licensors": [], "score_3_votes": 3, "url": "https://myanimelist.net/anime/27997/Kaitou_Tenshi_Twin_Angel__Kyun_Kyun%E2%98%86Tokimeki_Paradise_OVA", "popularity": 8524, "score_users": 54, "premiered": null, "aired_end": "2014-12-28T00:00:00", "aired_start": "2014-12-28T00:00:00", "synopsis": "The OVA will be pre-sold during the Comiket 87 starting on December 28, 2014, regular retail distribution of the limited edition package will start on January 30, 2015.", "score_8_votes": 8, "users_watching": 19, "score_2_votes": 0}